rabbitsay.py
RabbitSay-0.1.dist-info/DESCRIPTION.rst
RabbitSay-0.1.dist-info/entry_points.txt
RabbitSay-0.1.dist-info/METADATA
RabbitSay-0.1.dist-info/metadata.json
RabbitSay-0.1.dist-info/RECORD
RabbitSay-0.1.dist-info/top_level.txt
RabbitSay-0.1.dist-info/WHEEL
