Metadata-Version: 2.0
Name: RabbitSay
Version: 0.1
Summary: Say (possibly mean) things with a cute rabbit
Home-page: www.rabbitsay.wtf
Author: Chris Becker
Author-email: UNKNOWN
License: MIT
Platform: UNKNOWN
Classifier: Development Status :: 3 - Alpha
Classifier: License :: OSI Approved :: MIT License
Classifier: Programming Language :: Python
Classifier: Environment :: Console
Classifier: Topic :: Utilities
Requires-Dist: Click
